zenpi/__init__.py
zenpi/zenpi.py
zenpi-0.0.1.dist-info/LICENSE
zenpi-0.0.1.dist-info/METADATA
zenpi-0.0.1.dist-info/WHEEL
zenpi-0.0.1.dist-info/entry_points.txt
zenpi-0.0.1.dist-info/top_level.txt
zenpi-0.0.1.dist-info/RECORD
